entext/__init__.py
entext/entext.py
entext/open_ai.py
entext/ror.py
entext/settings.py
entext-0.0.5.dist-info/METADATA
entext-0.0.5.dist-info/WHEEL
entext-0.0.5.dist-info/top_level.txt
entext-0.0.5.dist-info/RECORD
